labpartner_uom/__init__.py
labpartner_uom/moduleAnalysis.py
labpartner_uom/moduleErrorProp.py
labpartner_uom-1.0.8.dist-info/LICENSE
labpartner_uom-1.0.8.dist-info/METADATA
labpartner_uom-1.0.8.dist-info/WHEEL
labpartner_uom-1.0.8.dist-info/top_level.txt
labpartner_uom-1.0.8.dist-info/RECORD
