Metadata-Version: 2.1
Name: labpartner_uom
Version: 1.0.8
Summary: Python Package with tools for Undergraduate Physics Laboratory
Home-page: https://github.com/SiddharthSule/labpartner_uom
Author: Siddharth Sule
Author-email: siddharth.sule@manchester.ac.uk
Project-URL: Documentation, https://github.com/SiddharthSule/labpartner_uom/docs
Project-URL: Bug Reports, https://github.com/SiddharthSule/labpartner_uom/issues
Project-URL: Source Code, https://github.com/SiddharthSule/labpartner_uom
Keywords: physics,laboratory,undergraduate,tools
Classifier: Development Status :: 5 - Production/Stable
Classifier: Intended Audience :: Education
Classifier: Topic :: Scientific/Engineering :: Physics
Classifier: Programming Language :: Python :: 3
Classifier: Programming Language :: Python :: 3.8
Classifier: Programming Language :: Python :: 3.9
Classifier: Programming Language :: Python :: 3.10
Classifier: Programming Language :: Python :: 3.11
Classifier: Programming Language :: Python :: 3 :: Only
Classifier: License :: OSI Approved :: GNU General Public License v3 (GPLv3)
Classifier: Operating System :: OS Independent
Requires-Python: >=3.8
License-File: LICENSE
Requires-Dist: numpy
Requires-Dist: sympy
Requires-Dist: scipy
Requires-Dist: matplotlib
Requires-Dist: pandas
Provides-Extra: dev
Requires-Dist: check-manifest ; extra == 'dev'
